bahy_bot_maker/__init__.py
bahy_bot_maker/main.py
bahy_bot_maker-0.4.dist-info/METADATA
bahy_bot_maker-0.4.dist-info/WHEEL
bahy_bot_maker-0.4.dist-info/entry_points.txt
bahy_bot_maker-0.4.dist-info/top_level.txt
bahy_bot_maker-0.4.dist-info/RECORD
